Trees/AVLTree.py
Trees/BST.py
Trees/BinaryTree.py
Trees/Heap.py
cs46_python_trees_gloriachoi-1.0.0.dist-info/DESCRIPTION.rst
cs46_python_trees_gloriachoi-1.0.0.dist-info/METADATA
cs46_python_trees_gloriachoi-1.0.0.dist-info/RECORD
cs46_python_trees_gloriachoi-1.0.0.dist-info/WHEEL
cs46_python_trees_gloriachoi-1.0.0.dist-info/metadata.json
cs46_python_trees_gloriachoi-1.0.0.dist-info/top_level.txt
