Metadata-Version: 2.0
Name: cs46-python-trees-gloriachoi
Version: 1.0.0
Summary: Python tree implementations of Binary Tree, BST, Heaps, and AVL
Home-page: https://github.com/gloriachoi99/trees
Author: Gloria Choi
Author-email: gchoi99@gmail.com
License: GPLv3
Platform: UNKNOWN
Classifier: Programming Language :: Python :: 3
Classifier: Programming Language :: Python :: 3.7
Requires-Dist: pytest
Requires-Dist: hypothesis
